android_arsenal_notifier/__init__.py
android_arsenal_notifier/android_arsenal.py
android_arsenal_notifier-0.2.0.dist-info/entry_points.txt
android_arsenal_notifier-0.2.0.dist-info/WHEEL
android_arsenal_notifier-0.2.0.dist-info/METADATA
android_arsenal_notifier-0.2.0.dist-info/RECORD
