Metadata-Version: 2.1
Name: android-arsenal-notifier
Version: 0.2.0
Summary: 
Keywords: android-arsenal,py-terminal-notifier,terminal-notifier,android arsenal,android,arsenal
Author: flomk
Author-email: sudogitrekt@gmail.com
Requires-Python: >=3.7,<4.0
Classifier: Programming Language :: Python :: 3
Classifier: Programming Language :: Python :: 3.7
Classifier: Programming Language :: Python :: 3.8
Requires-Dist: py-terminal-notifier (==0.1.0)
Requires-Dist: requests (>2.2-)
Requires-Dist: selectolax (>0.2.0)
